{
  "predicate": {
    "glow_intensity": 0.8749878970120528,
    "cognitive_mode": "GUARD-HABIT",
    "spatial_coordinate": {
      "node_id": "NODE_2_3",
      "recursion_depth": 3,
      "coordinates": [
        0.8200000000000001,
        0.3560000000000001,
        -0.738,
        0.1519999999999999,
        -0.974,
        -0.508,
        -0.45799999999999996,
        -0.24,
        0.08800000000000008,
        0.028000000000000025,
        -0.646,
        -0.926,
        0.06800000000000006,
        -0.838,
        0.31200000000000006,
        0.754,
        0.3500000000000001,
        -0.54
      ],
      "adjacency_value": 0.0
    },
    "epistemic_alignment": 0.676,
    "deterministic": false,
    "predictive_intent": {
      "prediction_type": "UNSURE",
      "confidence": 0.3,
      "hume_vivacity": 0.4
    },
    "jump_vector": [],
    "navigation_vector": [
      0.25335695182925955,
      -0.28526995670426697
    ],
    "final_verdict": "disagreement_detected",
    "final_verdict_source": "CALI_SKG"
  },
  "confidence": 0.8749878970120528,
  "triad_c_mode": "GUARD-HABIT",
  "field_density": 709,
  "ucm_envelope": {
    "stardate": 1775218075.9996524,
    "glyph_trace": "a9c4a2ab87e842849e87a3508d3d4fe45fc1e3b592a55b1fc968b3251951ea8c",
    "core_4": {
      "caleon": {
        "shadow": {
          "confidence": 0.959,
          "reference": "spinoza_monism_skg",
          "domain": "unknown"
        },
        "confidence": 0.959,
        "advisory_verdict": "monitor"
      },
      "kaygee": {
        "shadow": {
          "confidence": 0.608,
          "reference": "kant_critical_skg",
          "domain": "unknown"
        },
        "confidence": 0.608,
        "advisory_verdict": "monitor"
      },
      "cali_x_one": {
        "shadow": {
          "confidence": 0.555,
          "reference": "hume_skepticism_skg",
          "domain": "unknown"
        },
        "confidence": 0.555,
        "advisory_verdict": "monitor"
      },
      "ecm": {
        "convergence_weights": {
          "caleon": 0.3546597633136095,
          "kaygee": 0.22485207100591717,
          "cali_x_one": 0.20525147928994086,
          "empirical": 0.21523668639053256
        },
        "inputs": {
          "locke": {
            "confidence": 0.582,
            "reference": "locke_empiricism_skg",
            "domain": "unknown"
          },
          "hume": {
            "confidence": 0.555,
            "reference": "hume_skepticism_skg",
            "domain": "unknown"
          },
          "kant": {
            "confidence": 0.608,
            "reference": "kant_critical_skg",
            "domain": "unknown"
          },
          "spinoza": {
            "confidence": 0.959,
            "reference": "spinoza_monism_skg",
            "domain": "unknown"
          }
        },
        "note": "ECM emits convergence weights only (advisory)."
      }
    },
    "advisory_plus_one": {
      "advisory_only": true,
      "confidence_gradients": {
        "caleon": 0.4216513098402857,
        "kaygee": 0.2968356719195039,
        "cali_x_one": 0.2815130182402104
      },
      "tension_indicators": {
        "entropy": 1.0814971637157187,
        "spread": 0.4039999999999999,
        "reweight_recommended": true
      },
      "suggestion": "consider re-weighting high-tension lobes"
    },
    "cali_reflection": {
      "observational_only": true,
      "events": [
        {
          "type": "drift",
          "detail": "confidence spread exceeded threshold"
        },
        {
          "type": "anomaly",
          "detail": "high entropy in lobe gradients"
        }
      ],
      "flags": {
        "drift_detected": true,
        "anomaly_detected": true,
        "ethical_tension": false
      }
    },
    "final_verdict": "monitor",
    "final_verdict_source": "UCM Core-4 deliberation (ECM advisory only)",
    "confidence": 0.8749878970120528
  },
  "cali_reflection": {
    "observational_only": true,
    "events": [
      {
        "type": "drift",
        "detail": "confidence spread exceeded threshold"
      },
      {
        "type": "anomaly",
        "detail": "high entropy in lobe gradients"
      }
    ],
    "flags": {
      "drift_detected": true,
      "anomaly_detected": true,
      "ethical_tension": false
    }
  }
}