{
  "predicate": {
    "glow_intensity": 0.8732363029367106,
    "cognitive_mode": "GUARD-HABIT",
    "spatial_coordinate": {
      "node_id": "NODE_10_5",
      "recursion_depth": 5,
      "coordinates": [
        0.6739999999999999,
        -0.03600000000000003,
        -0.03600000000000003,
        -0.062000000000000055,
        0.5680000000000001,
        0.8180000000000001,
        0.47,
        0.254,
        0.030000000000000027,
        -0.628,
        -0.92,
        0.532,
        0.9199999999999999,
        -0.736,
        -0.548,
        0.30000000000000004,
        -0.09999999999999998,
        0.6240000000000001
      ],
      "adjacency_value": 0.0
    },
    "epistemic_alignment": 0.7585,
    "deterministic": false,
    "predictive_intent": {
      "prediction_type": "UNSURE",
      "confidence": 0.3,
      "hume_vivacity": 0.4
    },
    "jump_vector": [],
    "navigation_vector": [
      -1.1418776913675097,
      0.01456083513379277
    ],
    "final_verdict": "disagreement_detected",
    "final_verdict_source": "CALI_SKG"
  },
  "confidence": 0.8732363029367106,
  "triad_c_mode": "GUARD-HABIT",
  "field_density": 751,
  "ucm_envelope": {
    "stardate": 1775879996.6124172,
    "glyph_trace": "5c4c7a92e2adb92d2c4ceccdc1fdb49c065c061f8ee45be6cfa21e5cf9586a8c",
    "core_4": {
      "caleon": {
        "shadow": {
          "confidence": 0.743,
          "reference": "spinoza_monism_skg",
          "domain": "unknown"
        },
        "confidence": 0.743,
        "advisory_verdict": "monitor"
      },
      "kaygee": {
        "shadow": {
          "confidence": 0.71,
          "reference": "kant_critical_skg",
          "domain": "unknown"
        },
        "confidence": 0.71,
        "advisory_verdict": "monitor"
      },
      "cali_x_one": {
        "shadow": {
          "confidence": 0.814,
          "reference": "hume_skepticism_skg",
          "domain": "unknown"
        },
        "confidence": 0.814,
        "advisory_verdict": "monitor"
      },
      "ecm": {
        "convergence_weights": {
          "caleon": 0.24489123269611077,
          "kaygee": 0.23401450230718523,
          "cali_x_one": 0.2682926829268293,
          "empirical": 0.2528015820698748
        },
        "inputs": {
          "locke": {
            "confidence": 0.767,
            "reference": "locke_empiricism_skg",
            "domain": "unknown"
          },
          "hume": {
            "confidence": 0.814,
            "reference": "hume_skepticism_skg",
            "domain": "unknown"
          },
          "kant": {
            "confidence": 0.71,
            "reference": "kant_critical_skg",
            "domain": "unknown"
          },
          "spinoza": {
            "confidence": 0.743,
            "reference": "spinoza_monism_skg",
            "domain": "unknown"
          }
        },
        "note": "ECM emits convergence weights only (advisory)."
      }
    },
    "advisory_plus_one": {
      "advisory_only": true,
      "confidence_gradients": {
        "caleon": 0.3288262451160234,
        "kaygee": 0.31815207155462727,
        "cali_x_one": 0.35302168332934936
      },
      "tension_indicators": {
        "entropy": 1.0976602739180708,
        "spread": 0.10399999999999998,
        "reweight_recommended": true
      },
      "suggestion": "consider re-weighting high-tension lobes"
    },
    "cali_reflection": {
      "observational_only": true,
      "events": [
        {
          "type": "anomaly",
          "detail": "high entropy in lobe gradients"
        }
      ],
      "flags": {
        "drift_detected": false,
        "anomaly_detected": true,
        "ethical_tension": false
      }
    },
    "final_verdict": "monitor",
    "final_verdict_source": "UCM Core-4 deliberation (ECM advisory only)",
    "confidence": 0.8732363029367106
  },
  "cali_reflection": {
    "observational_only": true,
    "events": [
      {
        "type": "anomaly",
        "detail": "high entropy in lobe gradients"
      }
    ],
    "flags": {
      "drift_detected": false,
      "anomaly_detected": true,
      "ethical_tension": false
    }
  }
}