{
  "predicate": {
    "glow_intensity": 0.8732224965951659,
    "cognitive_mode": "GUARD-HABIT",
    "spatial_coordinate": {
      "node_id": "NODE_2_2",
      "recursion_depth": 2,
      "coordinates": [
        -0.24,
        -0.946,
        0.474,
        0.8200000000000001,
        -0.44399999999999995,
        -0.858,
        0.42199999999999993,
        0.3779999999999999,
        0.3460000000000001,
        0.3779999999999999,
        0.1439999999999999,
        -0.528,
        0.21199999999999997,
        -0.77,
        0.8200000000000001,
        -0.46399999999999997,
        -0.378,
        0.276
      ],
      "adjacency_value": 0.0
    },
    "epistemic_alignment": 0.7995,
    "deterministic": false,
    "predictive_intent": {
      "prediction_type": "UNSURE",
      "confidence": 0.3,
      "hume_vivacity": 0.4
    },
    "jump_vector": [],
    "navigation_vector": [
      0.07107987356687334,
      -0.24712911750821698
    ],
    "final_verdict": "disagreement_detected",
    "final_verdict_source": "CALI_SKG"
  },
  "confidence": 0.8732224965951659,
  "triad_c_mode": "GUARD-HABIT",
  "field_density": 133,
  "ucm_envelope": {
    "stardate": 1775041300.2005584,
    "glyph_trace": "4332bda7e2c52ef3910a31add3b111e93e48f407b1581392dd678a2947967abe",
    "core_4": {
      "caleon": {
        "shadow": {
          "confidence": 0.753,
          "reference": "spinoza_monism_skg",
          "domain": "unknown"
        },
        "confidence": 0.753,
        "advisory_verdict": "monitor"
      },
      "kaygee": {
        "shadow": {
          "confidence": 0.963,
          "reference": "kant_critical_skg",
          "domain": "unknown"
        },
        "confidence": 0.963,
        "advisory_verdict": "monitor"
      },
      "cali_x_one": {
        "shadow": {
          "confidence": 0.696,
          "reference": "hume_skepticism_skg",
          "domain": "unknown"
        },
        "confidence": 0.696,
        "advisory_verdict": "monitor"
      },
      "ecm": {
        "convergence_weights": {
          "caleon": 0.2354596622889306,
          "kaygee": 0.30112570356472795,
          "cali_x_one": 0.21763602251407127,
          "empirical": 0.2457786116322702
        },
        "inputs": {
          "locke": {
            "confidence": 0.786,
            "reference": "locke_empiricism_skg",
            "domain": "unknown"
          },
          "hume": {
            "confidence": 0.696,
            "reference": "hume_skepticism_skg",
            "domain": "unknown"
          },
          "kant": {
            "confidence": 0.963,
            "reference": "kant_critical_skg",
            "domain": "unknown"
          },
          "spinoza": {
            "confidence": 0.753,
            "reference": "spinoza_monism_skg",
            "domain": "unknown"
          }
        },
        "note": "ECM emits convergence weights only (advisory)."
      }
    },
    "advisory_plus_one": {
      "advisory_only": true,
      "confidence_gradients": {
        "caleon": 0.31463636822468216,
        "kaygee": 0.38815998434326143,
        "cali_x_one": 0.2972036474320564
      },
      "tension_indicators": {
        "entropy": 1.0917647017537806,
        "spread": 0.267,
        "reweight_recommended": true
      },
      "suggestion": "consider re-weighting high-tension lobes"
    },
    "cali_reflection": {
      "observational_only": true,
      "events": [
        {
          "type": "drift",
          "detail": "confidence spread exceeded threshold"
        },
        {
          "type": "anomaly",
          "detail": "high entropy in lobe gradients"
        }
      ],
      "flags": {
        "drift_detected": true,
        "anomaly_detected": true,
        "ethical_tension": false
      }
    },
    "final_verdict": "monitor",
    "final_verdict_source": "UCM Core-4 deliberation (ECM advisory only)",
    "confidence": 0.8732224965951659
  },
  "cali_reflection": {
    "observational_only": true,
    "events": [
      {
        "type": "drift",
        "detail": "confidence spread exceeded threshold"
      },
      {
        "type": "anomaly",
        "detail": "high entropy in lobe gradients"
      }
    ],
    "flags": {
      "drift_detected": true,
      "anomaly_detected": true,
      "ethical_tension": false
    }
  }
}