{
  "predicate": {
    "glow_intensity": 0.874540314590528,
    "cognitive_mode": "GUARD-HABIT",
    "spatial_coordinate": {
      "node_id": "NODE_12_3",
      "recursion_depth": 3,
      "coordinates": [
        -0.362,
        0.3520000000000001,
        -0.8,
        0.32600000000000007,
        -0.46599999999999997,
        -0.872,
        -0.616,
        0.782,
        -0.49,
        0.6659999999999999,
        0.22399999999999998,
        -0.19199999999999995,
        -0.10399999999999998,
        0.5680000000000001,
        0.1140000000000001,
        -0.5880000000000001,
        -0.79,
        0.46199999999999997
      ],
      "adjacency_value": 0.0
    },
    "epistemic_alignment": 0.7535000000000001,
    "deterministic": false,
    "predictive_intent": {
      "prediction_type": "UNSURE",
      "confidence": 0.3,
      "hume_vivacity": 0.4
    },
    "jump_vector": [],
    "navigation_vector": [
      0.24694215425931557,
      0.18202959908249888
    ],
    "final_verdict": "disagreement_detected",
    "final_verdict_source": "CALI_SKG"
  },
  "confidence": 0.874540314590528,
  "triad_c_mode": "GUARD-HABIT",
  "field_density": 763,
  "ucm_envelope": {
    "stardate": 1775051330.1777408,
    "glyph_trace": "2b608f0a6d889252627134e3744bd4df932877dac59b25922db102148418f68d",
    "core_4": {
      "caleon": {
        "shadow": {
          "confidence": 0.598,
          "reference": "spinoza_monism_skg",
          "domain": "unknown"
        },
        "confidence": 0.598,
        "advisory_verdict": "monitor"
      },
      "kaygee": {
        "shadow": {
          "confidence": 0.812,
          "reference": "kant_critical_skg",
          "domain": "unknown"
        },
        "confidence": 0.812,
        "advisory_verdict": "monitor"
      },
      "cali_x_one": {
        "shadow": {
          "confidence": 0.612,
          "reference": "hume_skepticism_skg",
          "domain": "unknown"
        },
        "confidence": 0.612,
        "advisory_verdict": "monitor"
      },
      "ecm": {
        "convergence_weights": {
          "caleon": 0.1984074319840743,
          "kaygee": 0.26940942269409424,
          "cali_x_one": 0.2030524220305242,
          "empirical": 0.3291307232913072
        },
        "inputs": {
          "locke": {
            "confidence": 0.992,
            "reference": "locke_empiricism_skg",
            "domain": "unknown"
          },
          "hume": {
            "confidence": 0.612,
            "reference": "hume_skepticism_skg",
            "domain": "unknown"
          },
          "kant": {
            "confidence": 0.812,
            "reference": "kant_critical_skg",
            "domain": "unknown"
          },
          "spinoza": {
            "confidence": 0.598,
            "reference": "spinoza_monism_skg",
            "domain": "unknown"
          }
        },
        "note": "ECM emits convergence weights only (advisory)."
      }
    },
    "advisory_plus_one": {
      "advisory_only": true,
      "confidence_gradients": {
        "caleon": 0.30743490297348913,
        "kaygee": 0.3807958356971906,
        "cali_x_one": 0.31176926132932026
      },
      "tension_indicators": {
        "entropy": 1.0936368302960549,
        "spread": 0.21400000000000008,
        "reweight_recommended": true
      },
      "suggestion": "consider re-weighting high-tension lobes"
    },
    "cali_reflection": {
      "observational_only": true,
      "events": [
        {
          "type": "drift",
          "detail": "confidence spread exceeded threshold"
        },
        {
          "type": "anomaly",
          "detail": "high entropy in lobe gradients"
        }
      ],
      "flags": {
        "drift_detected": true,
        "anomaly_detected": true,
        "ethical_tension": false
      }
    },
    "final_verdict": "monitor",
    "final_verdict_source": "UCM Core-4 deliberation (ECM advisory only)",
    "confidence": 0.874540314590528
  },
  "cali_reflection": {
    "observational_only": true,
    "events": [
      {
        "type": "drift",
        "detail": "confidence spread exceeded threshold"
      },
      {
        "type": "anomaly",
        "detail": "high entropy in lobe gradients"
      }
    ],
    "flags": {
      "drift_detected": true,
      "anomaly_detected": true,
      "ethical_tension": false
    }
  }
}