{
  "predicate": {
    "glow_intensity": 0.8744278610164131,
    "cognitive_mode": "GUARD-HABIT",
    "spatial_coordinate": {
      "node_id": "NODE_13_4",
      "recursion_depth": 4,
      "coordinates": [
        -0.5700000000000001,
        -0.052000000000000046,
        0.16999999999999993,
        0.71,
        -0.404,
        -0.556,
        0.8340000000000001,
        -0.842,
        0.006000000000000005,
        -0.8140000000000001,
        0.262,
        -0.030000000000000027,
        -0.09799999999999998,
        -0.33199999999999996,
        0.3839999999999999,
        0.996,
        0.28600000000000003,
        0.938
      ],
      "adjacency_value": 0.0
    },
    "epistemic_alignment": 0.7912499999999999,
    "deterministic": false,
    "predictive_intent": {
      "prediction_type": "UNSURE",
      "confidence": 0.3,
      "hume_vivacity": 0.4
    },
    "jump_vector": [],
    "navigation_vector": [
      -0.2862148814897077,
      0.3425070934409263
    ],
    "final_verdict": "disagreement_detected",
    "final_verdict_source": "CALI_SKG"
  },
  "confidence": 0.8744278610164131,
  "triad_c_mode": "GUARD-HABIT",
  "field_density": 675,
  "ucm_envelope": {
    "stardate": 1775896319.2240572,
    "glyph_trace": "f554dc9bd33e1ae2ceccaf19aa71868150428468a9c44816bb710f1e91ddb42e",
    "core_4": {
      "caleon": {
        "shadow": {
          "confidence": 0.969,
          "reference": "spinoza_monism_skg",
          "domain": "unknown"
        },
        "confidence": 0.969,
        "advisory_verdict": "monitor"
      },
      "kaygee": {
        "shadow": {
          "confidence": 0.957,
          "reference": "kant_critical_skg",
          "domain": "unknown"
        },
        "confidence": 0.957,
        "advisory_verdict": "monitor"
      },
      "cali_x_one": {
        "shadow": {
          "confidence": 0.61,
          "reference": "hume_skepticism_skg",
          "domain": "unknown"
        },
        "confidence": 0.61,
        "advisory_verdict": "monitor"
      },
      "ecm": {
        "convergence_weights": {
          "caleon": 0.3061611374407583,
          "kaygee": 0.30236966824644546,
          "cali_x_one": 0.19273301737756712,
          "empirical": 0.19873617693522908
        },
        "inputs": {
          "locke": {
            "confidence": 0.629,
            "reference": "locke_empiricism_skg",
            "domain": "unknown"
          },
          "hume": {
            "confidence": 0.61,
            "reference": "hume_skepticism_skg",
            "domain": "unknown"
          },
          "kant": {
            "confidence": 0.957,
            "reference": "kant_critical_skg",
            "domain": "unknown"
          },
          "spinoza": {
            "confidence": 0.969,
            "reference": "spinoza_monism_skg",
            "domain": "unknown"
          }
        },
        "note": "ECM emits convergence weights only (advisory)."
      }
    },
    "advisory_plus_one": {
      "advisory_only": true,
      "confidence_gradients": {
        "caleon": 0.37223900130403864,
        "kaygee": 0.3677988276124959,
        "cali_x_one": 0.25996217108346553
      },
      "tension_indicators": {
        "entropy": 1.0859591567352938,
        "spread": 0.359,
        "reweight_recommended": true
      },
      "suggestion": "consider re-weighting high-tension lobes"
    },
    "cali_reflection": {
      "observational_only": true,
      "events": [
        {
          "type": "drift",
          "detail": "confidence spread exceeded threshold"
        },
        {
          "type": "anomaly",
          "detail": "high entropy in lobe gradients"
        }
      ],
      "flags": {
        "drift_detected": true,
        "anomaly_detected": true,
        "ethical_tension": false
      }
    },
    "final_verdict": "monitor",
    "final_verdict_source": "UCM Core-4 deliberation (ECM advisory only)",
    "confidence": 0.8744278610164131
  },
  "cali_reflection": {
    "observational_only": true,
    "events": [
      {
        "type": "drift",
        "detail": "confidence spread exceeded threshold"
      },
      {
        "type": "anomaly",
        "detail": "high entropy in lobe gradients"
      }
    ],
    "flags": {
      "drift_detected": true,
      "anomaly_detected": true,
      "ethical_tension": false
    }
  }
}