{
  "predicate": {
    "glow_intensity": 0.8735327144116196,
    "cognitive_mode": "GUARD-HABIT",
    "spatial_coordinate": {
      "node_id": "NODE_3_4",
      "recursion_depth": 4,
      "coordinates": [
        -0.538,
        -0.6759999999999999,
        0.748,
        -0.46399999999999997,
        -0.88,
        0.014000000000000012,
        -0.5900000000000001,
        0.21199999999999997,
        0.43999999999999995,
        -0.862,
        0.976,
        0.9199999999999999,
        -0.384,
        0.694,
        -0.44199999999999995,
        0.020000000000000018,
        0.08000000000000007,
        0.010000000000000009
      ],
      "adjacency_value": 0.0
    },
    "epistemic_alignment": 0.724,
    "deterministic": false,
    "predictive_intent": {
      "prediction_type": "UNSURE",
      "confidence": 0.3,
      "hume_vivacity": 0.4
    },
    "jump_vector": [],
    "navigation_vector": [
      -0.4537764321901762,
      0.17847129785350563
    ],
    "final_verdict": "disagreement_detected",
    "final_verdict_source": "CALI_SKG"
  },
  "confidence": 0.8735327144116196,
  "triad_c_mode": "GUARD-HABIT",
  "field_density": 607,
  "ucm_envelope": {
    "stardate": 1775083272.6299734,
    "glyph_trace": "58adb9fd195d6fcf51c462fb58fecf049cd5cc34938ef7789cd24d4b7b9afb07",
    "core_4": {
      "caleon": {
        "shadow": {
          "confidence": 0.643,
          "reference": "spinoza_monism_skg",
          "domain": "unknown"
        },
        "confidence": 0.643,
        "advisory_verdict": "monitor"
      },
      "kaygee": {
        "shadow": {
          "confidence": 0.61,
          "reference": "kant_critical_skg",
          "domain": "unknown"
        },
        "confidence": 0.61,
        "advisory_verdict": "monitor"
      },
      "cali_x_one": {
        "shadow": {
          "confidence": 0.89,
          "reference": "hume_skepticism_skg",
          "domain": "unknown"
        },
        "confidence": 0.89,
        "advisory_verdict": "monitor"
      },
      "ecm": {
        "convergence_weights": {
          "caleon": 0.22203038674033146,
          "kaygee": 0.21063535911602208,
          "cali_x_one": 0.30732044198895025,
          "empirical": 0.2600138121546961
        },
        "inputs": {
          "locke": {
            "confidence": 0.753,
            "reference": "locke_empiricism_skg",
            "domain": "unknown"
          },
          "hume": {
            "confidence": 0.89,
            "reference": "hume_skepticism_skg",
            "domain": "unknown"
          },
          "kant": {
            "confidence": 0.61,
            "reference": "kant_critical_skg",
            "domain": "unknown"
          },
          "spinoza": {
            "confidence": 0.643,
            "reference": "spinoza_monism_skg",
            "domain": "unknown"
          }
        },
        "note": "ECM emits convergence weights only (advisory)."
      }
    },
    "advisory_plus_one": {
      "advisory_only": true,
      "confidence_gradients": {
        "caleon": 0.307908537896734,
        "kaygee": 0.29791338324177086,
        "cali_x_one": 0.3941780788614952
      },
      "tension_indicators": {
        "entropy": 1.0904216481573168,
        "spread": 0.28,
        "reweight_recommended": true
      },
      "suggestion": "consider re-weighting high-tension lobes"
    },
    "cali_reflection": {
      "observational_only": true,
      "events": [
        {
          "type": "drift",
          "detail": "confidence spread exceeded threshold"
        },
        {
          "type": "anomaly",
          "detail": "high entropy in lobe gradients"
        }
      ],
      "flags": {
        "drift_detected": true,
        "anomaly_detected": true,
        "ethical_tension": false
      }
    },
    "final_verdict": "monitor",
    "final_verdict_source": "UCM Core-4 deliberation (ECM advisory only)",
    "confidence": 0.8735327144116196
  },
  "cali_reflection": {
    "observational_only": true,
    "events": [
      {
        "type": "drift",
        "detail": "confidence spread exceeded threshold"
      },
      {
        "type": "anomaly",
        "detail": "high entropy in lobe gradients"
      }
    ],
    "flags": {
      "drift_detected": true,
      "anomaly_detected": true,
      "ethical_tension": false
    }
  }
}