{
  "predicate": {
    "glow_intensity": 0.8750362337158099,
    "cognitive_mode": "GUARD-HABIT",
    "spatial_coordinate": {
      "node_id": "NODE_10_2",
      "recursion_depth": 2,
      "coordinates": [
        -0.6659999999999999,
        0.3839999999999999,
        0.486,
        -0.492,
        0.56,
        -0.6739999999999999,
        -0.22599999999999998,
        -0.872,
        -0.040000000000000036,
        0.04800000000000004,
        -0.966,
        -0.18600000000000005,
        0.6599999999999999,
        0.988,
        -0.802,
        -0.642,
        0.786,
        -0.618
      ],
      "adjacency_value": 0.0
    },
    "epistemic_alignment": 0.6952499999999999,
    "deterministic": false,
    "predictive_intent": {
      "prediction_type": "UNSURE",
      "confidence": 0.3,
      "hume_vivacity": 0.4
    },
    "jump_vector": [],
    "navigation_vector": [
      -0.4473407139154758,
      -0.13518510594102418
    ],
    "final_verdict": "disagreement_detected",
    "final_verdict_source": "CALI_SKG"
  },
  "confidence": 0.8750362337158099,
  "triad_c_mode": "GUARD-HABIT",
  "field_density": 622,
  "ucm_envelope": {
    "stardate": 1776096008.949738,
    "glyph_trace": "628d59acbd699adc0305ca50387497f8924d51004e570e15a927d8d41630bf3c",
    "core_4": {
      "caleon": {
        "shadow": {
          "confidence": 0.694,
          "reference": "spinoza_monism_skg",
          "domain": "unknown"
        },
        "confidence": 0.694,
        "advisory_verdict": "monitor"
      },
      "kaygee": {
        "shadow": {
          "confidence": 0.518,
          "reference": "kant_critical_skg",
          "domain": "unknown"
        },
        "confidence": 0.518,
        "advisory_verdict": "monitor"
      },
      "cali_x_one": {
        "shadow": {
          "confidence": 0.894,
          "reference": "hume_skepticism_skg",
          "domain": "unknown"
        },
        "confidence": 0.894,
        "advisory_verdict": "monitor"
      },
      "ecm": {
        "convergence_weights": {
          "caleon": 0.2495505213951816,
          "kaygee": 0.18626393383674938,
          "cali_x_one": 0.32146709816612734,
          "empirical": 0.24271844660194178
        },
        "inputs": {
          "locke": {
            "confidence": 0.675,
            "reference": "locke_empiricism_skg",
            "domain": "unknown"
          },
          "hume": {
            "confidence": 0.894,
            "reference": "hume_skepticism_skg",
            "domain": "unknown"
          },
          "kant": {
            "confidence": 0.518,
            "reference": "kant_critical_skg",
            "domain": "unknown"
          },
          "spinoza": {
            "confidence": 0.694,
            "reference": "spinoza_monism_skg",
            "domain": "unknown"
          }
        },
        "note": "ECM emits convergence weights only (advisory)."
      }
    },
    "advisory_plus_one": {
      "advisory_only": true,
      "confidence_gradients": {
        "caleon": 0.32679517051597107,
        "kaygee": 0.2740563068623989,
        "cali_x_one": 0.3991485226216301
      },
      "tension_indicators": {
        "entropy": 1.0868258966918463,
        "spread": 0.376,
        "reweight_recommended": true
      },
      "suggestion": "consider re-weighting high-tension lobes"
    },
    "cali_reflection": {
      "observational_only": true,
      "events": [
        {
          "type": "drift",
          "detail": "confidence spread exceeded threshold"
        },
        {
          "type": "anomaly",
          "detail": "high entropy in lobe gradients"
        }
      ],
      "flags": {
        "drift_detected": true,
        "anomaly_detected": true,
        "ethical_tension": false
      }
    },
    "final_verdict": "monitor",
    "final_verdict_source": "UCM Core-4 deliberation (ECM advisory only)",
    "confidence": 0.8750362337158099
  },
  "cali_reflection": {
    "observational_only": true,
    "events": [
      {
        "type": "drift",
        "detail": "confidence spread exceeded threshold"
      },
      {
        "type": "anomaly",
        "detail": "high entropy in lobe gradients"
      }
    ],
    "flags": {
      "drift_detected": true,
      "anomaly_detected": true,
      "ethical_tension": false
    }
  }
}