{
  "predicate": {
    "glow_intensity": 0.8739341170225029,
    "cognitive_mode": "GUARD-HABIT",
    "spatial_coordinate": {
      "node_id": "NODE_8_6",
      "recursion_depth": 6,
      "coordinates": [
        -0.118,
        -0.15000000000000002,
        -0.05600000000000005,
        0.46799999999999997,
        -0.906,
        0.714,
        -0.5700000000000001,
        -0.43999999999999995,
        -0.10199999999999998,
        0.746,
        0.02200000000000002,
        -0.8280000000000001,
        -0.694,
        -0.522,
        0.5780000000000001,
        -0.938,
        0.30800000000000005,
        -0.6759999999999999
      ],
      "adjacency_value": 0.0
    },
    "epistemic_alignment": 0.72275,
    "deterministic": false,
    "predictive_intent": {
      "prediction_type": "QUADRANT_TRANSITION",
      "target": "SW",
      "confidence": 0.1,
      "hume_vivacity": 0.12
    },
    "jump_vector": [],
    "navigation_vector": [
      -0.6250171406318561,
      0.30979420788289436
    ],
    "final_verdict": "disagreement_detected",
    "final_verdict_source": "CALI_SKG"
  },
  "confidence": 0.8739341170225029,
  "triad_c_mode": "GUARD-HABIT",
  "field_density": 640,
  "ucm_envelope": {
    "stardate": 1775152535.7841954,
    "glyph_trace": "f2266f76112ce37e7a847ea56114275c300f23cf9c9d71385df6a5062b82b801",
    "core_4": {
      "caleon": {
        "shadow": {
          "confidence": 0.775,
          "reference": "spinoza_monism_skg",
          "domain": "unknown"
        },
        "confidence": 0.775,
        "advisory_verdict": "monitor"
      },
      "kaygee": {
        "shadow": {
          "confidence": 0.769,
          "reference": "kant_critical_skg",
          "domain": "unknown"
        },
        "confidence": 0.769,
        "advisory_verdict": "monitor"
      },
      "cali_x_one": {
        "shadow": {
          "confidence": 0.725,
          "reference": "hume_skepticism_skg",
          "domain": "unknown"
        },
        "confidence": 0.725,
        "advisory_verdict": "monitor"
      },
      "ecm": {
        "convergence_weights": {
          "caleon": 0.26807333102732617,
          "kaygee": 0.26599792459356625,
          "cali_x_one": 0.25077827741265996,
          "empirical": 0.2151504669664476
        },
        "inputs": {
          "locke": {
            "confidence": 0.622,
            "reference": "locke_empiricism_skg",
            "domain": "unknown"
          },
          "hume": {
            "confidence": 0.725,
            "reference": "hume_skepticism_skg",
            "domain": "unknown"
          },
          "kant": {
            "confidence": 0.769,
            "reference": "kant_critical_skg",
            "domain": "unknown"
          },
          "spinoza": {
            "confidence": 0.775,
            "reference": "spinoza_monism_skg",
            "domain": "unknown"
          }
        },
        "note": "ECM emits convergence weights only (advisory)."
      }
    },
    "advisory_plus_one": {
      "advisory_only": true,
      "confidence_gradients": {
        "caleon": 0.33953005234332456,
        "kaygee": 0.33749897136543755,
        "cali_x_one": 0.32297097629123794
      },
      "tension_indicators": {
        "entropy": 1.0983663561230625,
        "spread": 0.050000000000000044,
        "reweight_recommended": true
      },
      "suggestion": "consider re-weighting high-tension lobes"
    },
    "cali_reflection": {
      "observational_only": true,
      "events": [
        {
          "type": "anomaly",
          "detail": "high entropy in lobe gradients"
        }
      ],
      "flags": {
        "drift_detected": false,
        "anomaly_detected": true,
        "ethical_tension": false
      }
    },
    "final_verdict": "monitor",
    "final_verdict_source": "UCM Core-4 deliberation (ECM advisory only)",
    "confidence": 0.8739341170225029
  },
  "cali_reflection": {
    "observational_only": true,
    "events": [
      {
        "type": "anomaly",
        "detail": "high entropy in lobe gradients"
      }
    ],
    "flags": {
      "drift_detected": false,
      "anomaly_detected": true,
      "ethical_tension": false
    }
  }
}